runbox/__init__.py
runbox/__main__.py
runbox/build_stages/__init__.py
runbox/build_stages/exceptions.py
runbox/build_stages/pipeline.py
runbox/build_stages/pipeline_loaders.py
runbox/build_stages/stages.py
runbox/docker/__init__.py
runbox/docker/docker_api.py
runbox/docker/exceptions.py
runbox/docker/mount.py
runbox/docker/sandbox.py
runbox/docker/sandbox_builder.py
runbox/docker/utils.py
runbox/models.py
runbox/proto.py
runbox/py.typed
runbox/scoring/__init__.py
runbox/scoring/proto.py
runbox/scoring/scoring_strategies.py
runbox/scoring/scoring_system.py
runbox/shortucts.py
runbox/testing/__init__.py
runbox/testing/proto.py
runbox/testing/test_case.py
runbox/testing/test_suite.py
runbox/utils.py
runbox-0.6.6.dist-info/LICENSE
runbox-0.6.6.dist-info/WHEEL
runbox-0.6.6.dist-info/METADATA
runbox-0.6.6.dist-info/RECORD
